{
  "intent": "1BR / 1 bath narrow front-back-split smoke test, no carport. 8x10 lot with standard 2 m setbacks gives exactly the narrow-fp-01 reference plan's 4x6 m envelope (24 m2): bedroom+bath rear band, great room + galley kitchen front band with dining-counter divider and entry into the great room. kitchen_back_door off \u2014 the kitchen's rear wall is interior (bath behind it).",
  "lot_width": 8.0,
  "lot_depth": 10.0,
  "bedroom_count": 1,
  "must_haves": [
    "single common bath behind the kitchen on one plumbing line",
    "side-by-side great room + galley kitchen with dining counter",
    "no carport"
  ],
  "avoid": [],
  "occupancy_class": "R-1",
  "kitchen_back_door": false,
  "setbacks": {
    "front": 2.0,
    "rear": 2.0,
    "left": 2.0,
    "right": 2.0
  },
  "topology": "1s/1br/narrow/1s_1br_nw_front_back_split_bath_gr.json"
}
